{
    "name": "@ohos/ability",
    "version": "1.8.0",
    "publishAs": "code-segment",
    "description": "轻量级元能力框架子系统，是OpenHarmony为开发者提供的一套开发鸿蒙应用的开发框架",
    "scripts": {
        "install": "DEST_PATH=${DEP_BUNDLE_BASE}/foundation/aafwk &&mkdir -p $DEST_PATH && cp -r ./* $DEST_PATH"
    },
    "keywords": [
        "ability"
    ],
    "license": "Apache V2",
    "repository": "",
    "homepage": "",
    "tags": [
        "foundation"
    ],
    "ohos": {
        "os": "1.0.0",
        "kernel": "liteos-a",
        "board": "hi3516,hi3518"
    }
}